Metadata-Version: 2.1
Name: biorxiv-retriever
Version: 0.20.1
Summary: Simple retriever for Biorxiv articles
Home-page: https://github.com/TalSchuster/BiorxivRetriever/
Author: Tal Schuster
Author-email: my.email@mit.edu
License: MIT
Download-URL: https://github.com/TalSchuster/BiorxivRetriever/biorxiv_retriever/v_0_20_1.tar.gz
Keywords: Biology,Rxivist,Biorxiv,retriever
Platform: UNKNOWN
Classifier: Development Status :: 3 - Alpha
Classifier: Intended Audience :: Developers
Classifier: Topic :: Software Development :: Build Tools
Classifier: License :: OSI Approved :: MIT License
Classifier: Programming Language :: Python :: 3
Classifier: Programming Language :: Python :: 3.4
Classifier: Programming Language :: Python :: 3.5
Classifier: Programming Language :: Python :: 3.6
Classifier: Programming Language :: Python :: 3.7
Classifier: Programming Language :: Python :: 3.8
